AUTHORS.rst
CONTRIBUTING.rst
HISTORY.rst
LICENSE
MANIFEST.in
README.rst
setup.cfg
setup.py
docs/Makefile
docs/authors.rst
docs/conf.py
docs/contributing.rst
docs/history.rst
docs/index.rst
docs/installation.rst
docs/make.bat
docs/readme.rst
docs/usage.rst
spotiminder/__init__.py
spotiminder/cli.py
spotiminder/spotiminder.py
spotiminder.egg-info/PKG-INFO
spotiminder.egg-info/SOURCES.txt
spotiminder.egg-info/dependency_links.txt
spotiminder.egg-info/entry_points.txt
spotiminder.egg-info/not-zip-safe
spotiminder.egg-info/requires.txt
spotiminder.egg-info/top_level.txt
tests/__init__.py
tests/test_spotiminder.py