Metadata-Version: 2.1
Name: spotiminder
Version: 0.1.9
Summary: A Python package to help keep your Spotify playlist metadata up-to-date when it is modified without your approval.
Home-page: https://github.com/willdinkel/spotiminder
Author: Will Dinkel
Author-email: wdinkel@gmail.com
License: MIT license
Keywords: spotiminder
Platform: UNKNOWN
Classifier: Development Status :: 2 - Pre-Alpha
Classifier: Intended Audience :: Developers
Classifier: License :: OSI Approved :: MIT License
Classifier: Natural Language :: English
Classifier: Programming Language :: Python :: 3
Classifier: Programming Language :: Python :: 3.6
Classifier: Programming Language :: Python :: 3.7
Classifier: Programming Language :: Python :: 3.8
Requires-Python: >=3.6
